theflow/__init__.py
theflow/base.py
theflow/callbacks.py
theflow/cli.py
theflow/config.py
theflow/context.py
theflow/debug.py
theflow/exceptions.py
theflow/middleware.py
theflow/safe.py
theflow/visualization.py
theflow/backends/__init__.py
theflow/backends/base.py
theflow/backends/http_sync.py
theflow/cache/__init__.py
theflow/cache/base.py
theflow/cache/filebased.py
theflow/cache/memcached.py
theflow/cache/memory.py
theflow/runs/__init__.py
theflow/runs/base.py
theflow/settings/__init__.py
theflow/settings/default.py
theflow/storage/__init__.py
theflow/storage/base.py
theflow/storage/local.py
theflow/utils/__init__.py
theflow/utils/documentation.py
theflow/utils/hashes.py
theflow/utils/modules.py
theflow/utils/multiprocess.py
theflow/utils/paths.py
theflow/utils/pretties.py
theflow/utils/typings.py
theflow-0.8.6.dist-info/LICENSE
theflow-0.8.6.dist-info/METADATA
theflow-0.8.6.dist-info/WHEEL
theflow-0.8.6.dist-info/top_level.txt
theflow-0.8.6.dist-info/RECORD
