Metadata-Version: 2.1
Name: theflow
Version: 0.8.6
Summary: A simple framework to build and run flows
Author-email: trducng <trungduc1992@gmail.com>
License: MIT
Project-URL: Homepage, https://github.com/trducng/theflow
Project-URL: Repository, https://github.com/trducng/theflow
Classifier: Programming Language :: Python :: 3
Classifier: Development Status :: 2 - Pre-Alpha
Requires-Python: >=3.8
License-File: LICENSE
Requires-Dist: pyyaml
Requires-Dist: diskcache
Requires-Dist: typing_extensions
Provides-Extra: dev
Requires-Dist: coverage; extra == "dev"
Requires-Dist: pytest; extra == "dev"
Requires-Dist: pytest-cov; extra == "dev"
Requires-Dist: black; extra == "dev"
Requires-Dist: flake8; extra == "dev"
Requires-Dist: mypy; extra == "dev"
Requires-Dist: isort; extra == "dev"
Requires-Dist: pre-commit; extra == "dev"
Requires-Dist: notebook; extra == "dev"
Requires-Dist: ipython; extra == "dev"
Requires-Dist: build; extra == "dev"
Requires-Dist: twine; extra == "dev"
Requires-Dist: papermill; extra == "dev"
Requires-Dist: pymemcache; extra == "dev"
